pybedforms/__init__.py
pybedforms/dune_topo.py
pybedforms/new_dunes.py
pybedforms-0.1.0.dist-info/LICENSE
pybedforms-0.1.0.dist-info/METADATA
pybedforms-0.1.0.dist-info/WHEEL
pybedforms-0.1.0.dist-info/top_level.txt
pybedforms-0.1.0.dist-info/RECORD
