Metadata-Version: 2.1
Name: pybedforms
Version: 0.1.0
Summary: Python implementation of Bedforms 4.0 for Simulating Bedforms and Cross-Bedding
Home-page: https://github.com/andrewannex/pybedforms
Author: Andrew M. Annex
Author-email: annex@jhu.edu
License: BSD-3-Clause
Keywords: usgs,dunes,simulation,geology,sedimentology
Platform: UNKNOWN
Classifier: Natural Language :: English
Classifier: License :: OSI Approved :: BSD License
Classifier: Development Status :: 3 - Alpha
Classifier: Intended Audience :: Science/Research
Classifier: Programming Language :: Python :: 3.6
Classifier: Programming Language :: Python :: 3.7
Classifier: Programming Language :: Python :: 3.8
Classifier: Programming Language :: Python :: 3.9
Requires: numpy
Requires: tqdm
Requires: scikitimage
Requires: scipy
Requires: matplotlib
Requires: mayavi
Requires: PyQt5
